<?xml version="1.0" encoding="UTF-8"?>
<objects serializationModel="Studio.02.00.00">
	<object class="AudioFile" id="{7d216708-5b87-4cf8-953f-3a4e01f11c77}">
		<property name="assetPath">
			<value>Project_Amnesia_SFX/PC/Attack/Sword/BRS_Sword_Schwing_Fast_Thin_3.wav</value>
		</property>
		<property name="frequencyInKHz">
			<value>44.0999985</value>
		</property>
		<property name="channelCount">
			<value>1</value>
		</property>
		<property name="length">
			<value>1.1493877551020408</value>
		</property>
		<relationship name="masterAssetFolder">
			<destination>{3cca5829-0569-4554-914f-05a525d4bd32}</destination>
		</relationship>
	</object>
</objects>
